caterva2/__init__.py
caterva2/api_utils.py
caterva2/client.py
caterva2/hdf5.py
caterva2/models.py
caterva2/utils.py
caterva2/clients/agent.py
caterva2/clients/cli.py
caterva2/services/db.py
caterva2/services/schemas.py
caterva2/services/server.py
caterva2/services/settings.py
caterva2/services/srv_utils.py
caterva2/services/users.py
caterva2/services/plugins/image/__init__.py
caterva2/services/plugins/image/templates/display.html
caterva2/services/plugins/tomography/__init__.py
caterva2/services/plugins/tomography/templates/display.html
caterva2/services/static/logo-caterva2-16x16.png
caterva2/services/static/logo-caterva2-32x32.png
caterva2/services/static/logo-caterva2-horizontal-small.webp
caterva2/services/static/build/main-BBYmTrE7.js
caterva2/services/static/build/main-Bl4lbrCH.css
caterva2/services/static/build/manifest.json
caterva2/services/static/vendor/fontawesome-6.5.1.min.css
caterva2/services/static/vendor/htmx-2.0.1.min.js
caterva2/services/static/vendor/htmx-2.0.2.min.js
caterva2/services/static/vendor/htmx-idiomorph-ext-0.3.0.min.js
caterva2/services/static/webfonts/fa-brands-400.ttf
caterva2/services/static/webfonts/fa-brands-400.woff2
caterva2/services/static/webfonts/fa-regular-400.ttf
caterva2/services/static/webfonts/fa-regular-400.woff2
caterva2/services/static/webfonts/fa-solid-900.ttf
caterva2/services/static/webfonts/fa-solid-900.woff2
caterva2/services/static/webfonts/fa-v4compatibility.ttf
caterva2/services/static/webfonts/fa-v4compatibility.woff2
caterva2/services/templates/base_anon.html
caterva2/services/templates/display_image.html
caterva2/services/templates/error.html
caterva2/services/templates/forgot-password-ok.html
caterva2/services/templates/forgot-password.html
caterva2/services/templates/home.html
caterva2/services/templates/info.html
caterva2/services/templates/info_view.html
caterva2/services/templates/login.html
caterva2/services/templates/logout.html
caterva2/services/templates/message.html
caterva2-2025.12.3.dist-info/METADATA
caterva2-2025.12.3.dist-info/WHEEL
caterva2-2025.12.3.dist-info/entry_points.txt
caterva2-2025.12.3.dist-info/licenses/LICENSE.txt
caterva2-2025.12.3.dist-info/RECORD
