Metadata-Version: 2.4
Name: caterva2
Version: 2025.12.3
Summary: A high-performance storage and computation system for Blosc2 datasets
Project-URL: Home, https://github.com/ironArray/Caterva2
Author-email: ironArray SLU <contact@ironarray.io>
License: GNU Affero General Public License version 3
License-File: LICENSE.txt
Keywords: blosc2
Classifier: Development Status :: 5 - Production/Stable
Classifier: Intended Audience :: Developers
Classifier: Intended Audience :: End Users/Desktop
Classifier: Intended Audience :: Information Technology
Classifier: License :: OSI Approved :: GNU Affero General Public License v3 or later (AGPLv3+)
Classifier: Operating System :: Microsoft :: Windows
Classifier: Operating System :: Unix
Classifier: Programming Language :: Python :: 3
Classifier: Programming Language :: Python :: 3.11
Classifier: Programming Language :: Python :: 3.12
Classifier: Programming Language :: Python :: 3.13
Classifier: Programming Language :: Python :: 3.14
Classifier: Topic :: Software Development :: Libraries :: Python Modules
Requires-Python: >=3.11
Requires-Dist: blosc2>=3.12.1
Requires-Dist: httpx[http2]
Provides-Extra: agent
Requires-Dist: watchfiles; extra == 'agent'
Provides-Extra: base-services
Requires-Dist: fastapi>=0.109; extra == 'base-services'
Requires-Dist: pydantic>=2; extra == 'base-services'
Requires-Dist: safer; extra == 'base-services'
Requires-Dist: uvicorn; extra == 'base-services'
Provides-Extra: blosc2-plugins
Requires-Dist: blosc2-grok; extra == 'blosc2-plugins'
Provides-Extra: clients
Requires-Dist: rich; extra == 'clients'
Requires-Dist: textual; extra == 'clients'
Provides-Extra: dev
Requires-Dist: pre-commit; extra == 'dev'
Requires-Dist: pytest; extra == 'dev'
Requires-Dist: pytest-cov; extra == 'dev'
Requires-Dist: ruff; extra == 'dev'
Provides-Extra: hdf5
Requires-Dist: b2h5py>=0.5.1; extra == 'hdf5'
Requires-Dist: h5py; extra == 'hdf5'
Requires-Dist: hdf5plugin; extra == 'hdf5'
Requires-Dist: msgpack; extra == 'hdf5'
Provides-Extra: server
Requires-Dist: aiosqlite; extra == 'server'
Requires-Dist: fastapi-mail; extra == 'server'
Requires-Dist: fastapi-users[sqlalchemy]; extra == 'server'
Requires-Dist: fastapi>=0.109; extra == 'server'
Requires-Dist: furl; extra == 'server'
Requires-Dist: jinja2; extra == 'server'
Requires-Dist: jupyterlite-core[contents]==0.6.2; extra == 'server'
Requires-Dist: jupyterlite-pyodide-kernel==0.6.1; extra == 'server'
Requires-Dist: markdown; extra == 'server'
Requires-Dist: nbconvert; extra == 'server'
Requires-Dist: pillow; extra == 'server'
Requires-Dist: pydantic>=2; extra == 'server'
Requires-Dist: pygments; extra == 'server'
Requires-Dist: python-dotenv; extra == 'server'
Requires-Dist: python-multipart; extra == 'server'
Requires-Dist: safer; extra == 'server'
Requires-Dist: uvicorn; extra == 'server'
Requires-Dist: uvicorn[standard]; extra == 'server'
Provides-Extra: services
Requires-Dist: aiosqlite; extra == 'services'
Requires-Dist: b2h5py>=0.5.1; extra == 'services'
Requires-Dist: fastapi-mail; extra == 'services'
Requires-Dist: fastapi-users[sqlalchemy]; extra == 'services'
Requires-Dist: fastapi>=0.109; extra == 'services'
Requires-Dist: furl; extra == 'services'
Requires-Dist: h5py; extra == 'services'
Requires-Dist: hdf5plugin; extra == 'services'
Requires-Dist: jinja2; extra == 'services'
Requires-Dist: jupyterlite-core[contents]==0.6.2; extra == 'services'
Requires-Dist: jupyterlite-pyodide-kernel==0.6.1; extra == 'services'
Requires-Dist: markdown; extra == 'services'
Requires-Dist: msgpack; extra == 'services'
Requires-Dist: nbconvert; extra == 'services'
Requires-Dist: pillow; extra == 'services'
Requires-Dist: pydantic>=2; extra == 'services'
Requires-Dist: pygments; extra == 'services'
Requires-Dist: python-dotenv; extra == 'services'
Requires-Dist: python-multipart; extra == 'services'
Requires-Dist: safer; extra == 'services'
Requires-Dist: uvicorn; extra == 'services'
Requires-Dist: uvicorn[standard]; extra == 'services'
Provides-Extra: tests
Requires-Dist: aiosqlite; extra == 'tests'
Requires-Dist: b2h5py>=0.5.1; extra == 'tests'
Requires-Dist: fastapi-mail; extra == 'tests'
Requires-Dist: fastapi-users[sqlalchemy]; extra == 'tests'
Requires-Dist: fastapi>=0.109; extra == 'tests'
Requires-Dist: furl; extra == 'tests'
Requires-Dist: h5py; extra == 'tests'
Requires-Dist: hdf5plugin; extra == 'tests'
Requires-Dist: jinja2; extra == 'tests'
Requires-Dist: jupyterlite-core[contents]==0.6.2; extra == 'tests'
Requires-Dist: jupyterlite-pyodide-kernel==0.6.1; extra == 'tests'
Requires-Dist: markdown; extra == 'tests'
Requires-Dist: msgpack; extra == 'tests'
Requires-Dist: nbconvert; extra == 'tests'
Requires-Dist: pillow; extra == 'tests'
Requires-Dist: pydantic>=2; extra == 'tests'
Requires-Dist: pygments; extra == 'tests'
Requires-Dist: pytest<8; extra == 'tests'
Requires-Dist: python-dotenv; extra == 'tests'
Requires-Dist: python-multipart; extra == 'tests'
Requires-Dist: rich; extra == 'tests'
Requires-Dist: safer; extra == 'tests'
Requires-Dist: textual; extra == 'tests'
Requires-Dist: uvicorn; extra == 'tests'
Requires-Dist: uvicorn[standard]; extra == 'tests'
Provides-Extra: tools
Requires-Dist: b2h5py>=0.5.1; extra == 'tools'
Requires-Dist: h5py; extra == 'tools'
Requires-Dist: hdf5plugin; extra == 'tools'
Requires-Dist: msgpack; extra == 'tools'
